{
  "entries": [
    {
      "idx": 0,
      "when": 1766459999000,
      "tag": "0000_initial",
      "breakpoints": true
    },
    {
      "idx": 1,
      "when": 1767055854000,
      "tag": "0001_regenerate_requests",
      "breakpoints": true
    },
    {
      "idx": 2,
      "when": 1767055855000,
      "tag": "0002_stripe_billing",
      "breakpoints": true
    },
    {
      "idx": 3,
      "when": 1767768789347,
      "tag": "0003_github_oauth",
      "breakpoints": true
    },
    {
      "idx": 4,
      "version": "7",
      "when": 1767938396666,
      "tag": "0004_add_conversion_columns",
      "breakpoints": true
    }
  ]
}